{
  "Avatar: Fire and Ash [IMAX 3D | English]": {
    "shows": 1,
    "gross": 27590.0,
    "sold": 77,
    "totalSeats": 316,
    "venues": 1,
    "cities": 1,
    "fastfilling": 0,
    "housefull": 0,
    "occupancy": 24.37
  },
  "Avatar: Fire and Ash [3D | Hindi]": {
    "shows": 1,
    "gross": 5640.0,
    "sold": 21,
    "totalSeats": 135,
    "venues": 1,
    "cities": 1,
    "fastfilling": 0,
    "housefull": 0,
    "occupancy": 15.56
  },
  "Avatar: Fire and Ash [4DX 3D | English]": {
    "shows": 2,
    "gross": 67600.0,
    "sold": 166,
    "totalSeats": 176,
    "venues": 2,
    "cities": 1,
    "fastfilling": 2,
    "housefull": 0,
    "occupancy": 94.32
  },
  "Dhurandhar [2D | Hindi]": {
    "shows": 2,
    "gross": 1450.0,
    "sold": 7,
    "totalSeats": 224,
    "venues": 2,
    "cities": 2,
    "fastfilling": 0,
    "housefull": 0,
    "occupancy": 3.12
  }
}