{
  "Avatar: Fire and Ash [IMAX 3D | English]": {
    "shows": 2,
    "gross": 44500.0,
    "sold": 103,
    "totalSeats": 650,
    "venues": 2,
    "cities": 2,
    "fastfilling": 0,
    "housefull": 0,
    "occupancy": 15.85
  },
  "Avatar: Fire and Ash [2D | Hindi]": {
    "shows": 1,
    "gross": 0.0,
    "sold": 0,
    "totalSeats": 70,
    "venues": 1,
    "cities": 1,
    "fastfilling": 0,
    "housefull": 0,
    "occupancy": 0.0
  },
  "Dhurandhar [2D | Hindi]": {
    "shows": 4,
    "gross": 46260.0,
    "sold": 214,
    "totalSeats": 956,
    "venues": 4,
    "cities": 3,
    "fastfilling": 0,
    "housefull": 0,
    "occupancy": 22.38
  },
  "Avatar: Fire and Ash [3D | Hindi]": {
    "shows": 3,
    "gross": 6960.0,
    "sold": 27,
    "totalSeats": 384,
    "venues": 3,
    "cities": 2,
    "fastfilling": 0,
    "housefull": 0,
    "occupancy": 7.03
  }
}