[
  {
    "movie": "Dhurandhar [2D | Hindi]",
    "venue": "PVR: Treasure Island, Bhilai",
    "address": "1st Floor, Treasure Island Mall, Surya Vihar, Smriti Nagar, Street Number 2, Bhilai, Chhattisgarh 490020, India",
    "chain": "PVR",
    "time": "08:00 AM",
    "audi": "",
    "session_id": "15245",
    "totalSeats": 148,
    "available": 148,
    "sold": 0,
    "gross": 0.0,
    "minsLeft": 196.3,
    "city": "Bhilai",
    "state": "Chhattisgarh",
    "source": "BMS",
    "date": "20251220"
  },
  {
    "movie": "Avatar: Fire and Ash [3D | English]",
    "venue": "Miraj Cinemas: MDR Mall, Chandrapur",
    "address": "MDR Mall and Multiplex, Survey No.-59, Wadgaon Bapat Nagar, Chandrapur, Maharashtra 442401, India",
    "chain": "Miraj Cinemas",
    "time": "07:15 AM",
    "audi": "",
    "session_id": "32776",
    "totalSeats": 228,
    "available": 228,
    "sold": 0,
    "gross": 0.0,
    "minsLeft": 150.9,
    "city": "Chandrapur",
    "state": "Maharashtra",
    "source": "BMS",
    "date": "20251220"
  },
  {
    "movie": "Dhurandhar [2D | Hindi]",
    "venue": "Connplex Cinemas: Rajkot",
    "address": "2nd Ring Road, Serenity Garden Road, Near Valupani restaurant, Rajkot, Gujarat 360004, India",
    "chain": "Connplex Cinemas Ltd",
    "time": "08:00 AM",
    "audi": "COUPLE SEATS",
    "session_id": "5812",
    "totalSeats": 50,
    "available": 36,
    "sold": 14,
    "gross": 3500.0,
    "minsLeft": 195.7,
    "city": "Rajkot",
    "state": "Gujarat",
    "source": "BMS",
    "date": "20251220"
  },
  {
    "movie": "Dhurandhar [2D | Hindi]",
    "venue": "Cinepolis Vandana: Rajkot",
    "address": "Vandana Heritage 4th  and 5th Floor, Opposite Atika Railway Crossing, Gondal Road, Rajkot, Gujarat 360004, India",
    "chain": "Cinepolis",
    "time": "08:00 AM",
    "audi": "2K LASER DOLBY 7.1",
    "session_id": "21706",
    "totalSeats": 211,
    "available": 202,
    "sold": 9,
    "gross": 2140.0,
    "minsLeft": 195.6,
    "city": "Rajkot",
    "state": "Gujarat",
    "source": "BMS",
    "date": "20251220"
  },
  {
    "movie": "Dhurandhar [2D | Hindi]",
    "venue": "INOX: Rajkot R World",
    "address": "Old Dharam Cinema Building, Kasturba Road, Naval Nagar, Near Saurashtra Cricket Association, Rajkot, Gujarat 360001, India",
    "chain": "INOX",
    "time": "07:15 AM",
    "audi": "",
    "session_id": "56342",
    "totalSeats": 172,
    "available": 172,
    "sold": 0,
    "gross": 0.0,
    "minsLeft": 150.6,
    "city": "Rajkot",
    "state": "Gujarat",
    "source": "BMS",
    "date": "20251220"
  },
  {
    "movie": "Avatar: Fire and Ash [3D | Hindi]",
    "venue": "INOX: Rajkot R World",
    "address": "Old Dharam Cinema Building, Kasturba Road, Naval Nagar, Near Saurashtra Cricket Association, Rajkot, Gujarat 360001, India",
    "chain": "INOX",
    "time": "07:30 AM",
    "audi": "",
    "session_id": "56315",
    "totalSeats": 174,
    "available": 174,
    "sold": 0,
    "gross": 0.0,
    "minsLeft": 165.6,
    "city": "Rajkot",
    "state": "Gujarat",
    "source": "BMS",
    "date": "20251220"
  },
  {
    "movie": "Dhurandhar [2D | Hindi]",
    "venue": "INOX: Reliance Mega Mall, Rajkot",
    "address": "INOX Leisure Ltd., 2nd Floor, Reliance Mall, 150 Feet Ring Road, Near Nana Mauva Circle, Rajkot, Gujarat 360005, India",
    "chain": "INOX",
    "time": "07:45 AM",
    "audi": "",
    "session_id": "50339",
    "totalSeats": 108,
    "available": 106,
    "sold": 2,
    "gross": 480.0,
    "minsLeft": 180.6,
    "city": "Rajkot",
    "state": "Gujarat",
    "source": "BMS",
    "date": "20251220"
  },
  {
    "movie": "Avatar: Fire and Ash [3D | Hindi]",
    "venue": "Rajhans Cinemas, R Square Mall: Vapi",
    "address": "Jayshree cinema compound, Daman Road, Chala, Vapi, Gujarat 396191, India",
    "chain": "Rajhans Cinemas",
    "time": "08:00 AM",
    "audi": "ATMOS",
    "session_id": "15562",
    "totalSeats": 217,
    "available": 195,
    "sold": 22,
    "gross": 5720.0,
    "minsLeft": 194.5,
    "city": "Vapi",
    "state": "Gujarat",
    "source": "BMS",
    "date": "20251220"
  },
  {
    "movie": "Dhurandhar [2D | Hindi]",
    "venue": "Miraj Cinemas: Citypride Multiplex, Jasdan",
    "address": "Ring Road, Atkot Road, Aanand Nagar, Jasdan, Gujarat 360050, India",
    "chain": "Miraj Cinemas",
    "time": "08:00 AM",
    "audi": "",
    "session_id": "1332",
    "totalSeats": 228,
    "available": 228,
    "sold": 0,
    "gross": 0.0,
    "minsLeft": 193.8,
    "city": "Jasdan",
    "state": "Gujarat",
    "source": "BMS",
    "date": "20251220"
  },
  {
    "movie": "Avatar: Fire and Ash [3D | Hindi]",
    "venue": "Santoshimata: Beed",
    "address": "Shahu Nagar, Pangri Road, Near Bus Stand, Beed, Maharashtra 431122, India",
    "chain": "E-SQUARE",
    "time": "08:00 AM",
    "audi": "2K DOLBY 7.1",
    "session_id": "85208",
    "totalSeats": 208,
    "available": 208,
    "sold": 0,
    "gross": 0.0,
    "minsLeft": 193.5,
    "city": "Beed",
    "state": "Maharashtra",
    "source": "BMS",
    "date": "20251220"
  },
  {
    "movie": "Avatar: Fire and Ash [3D | English]",
    "venue": "Savin Cinemas: Siliguri",
    "address": "Savin Plaza, Savin Kingdom,Hill Kart Road, Dagapur, Behind Baba Loknath Mandir, Siliguri, West Bengal 734003, India",
    "chain": "Savin World Resorts Pvt Ltd",
    "time": "08:00 AM",
    "audi": "",
    "session_id": "68003",
    "totalSeats": 297,
    "available": 280,
    "sold": 17,
    "gross": 3050.0,
    "minsLeft": 192.8,
    "city": "Siliguri",
    "state": "West Bengal",
    "source": "BMS",
    "date": "20251220"
  }
]